Workbook

Sheet Executive Summary
A1: Private vs PSU Banks in India — Strategic Analysis (FY20–FY25)
A2: 6 banks · 6 years · ₹50+ lakh crore of assets. Prepared by Priyanshu Moudgil · BBA · Business Analyst Portfolio.
A4: The Big Picture (FY25)
A5: Metric | B5: Private avg | C5: PSU avg | D5: Gap (pp) | E5: Direction | F5: Take-away
A6: ROA (%) | B6: =AVERAGEIFS('Raw Data'!I:I,'Raw Data'!B:B,"Private",'Raw Data'!C:C,"FY25") -> 1.9833333 | C6: =AVERAGEIFS('Raw Data'!I:I,'Raw Data'!B:B,"PSU",'Raw Data'!C:C,"FY25") -> 1.12 | D6: =B6-C6 -> 0.86333333 | E6: ↑ widening | F6: Private banks earn ~2× more per ₹ of assets.
A7: Gross NPA (%) | B7: =AVERAGEIFS('Raw Data'!H:H,'Raw Data'!B:B,"Private",'Raw Data'!C:C,"FY25") -> 1.4433333 | C7: =AVERAGEIFS('Raw Data'!H:H,'Raw Data'!B:B,"PSU",'Raw Data'!C:C,"FY25") -> 2.6766667 | D7: =C7-B7 -> 1.2333333 | E7: ↓ narrowing | F7: PSU NPA clean-up cut excess NPA from 6pp to 1pp.
A8: NIM (%) | B8: =AVERAGEIFS('Raw Data'!J:J,'Raw Data'!B:B,"Private",'Raw Data'!C:C,"FY25") -> 4.0933333 | C8: =AVERAGEIFS('Raw Data'!J:J,'Raw Data'!B:B,"PSU",'Raw Data'!C:C,"FY25") -> 3.0133333 | D8: =B8-C8 -> 1.08 | E8: → stable | F8: ~90bps structural spread on the lending side.
A9: CASA (%) | B9: =AVERAGEIFS('Raw Data'!K:K,'Raw Data'!B:B,"Private",'Raw Data'!C:C,"FY25") -> 38.1 | C9: =AVERAGEIFS('Raw Data'!K:K,'Raw Data'!B:B,"PSU",'Raw Data'!C:C,"FY25") -> 39.573333 | D9: =B9-C9 -> -1.4733333 | E9: ↓ flipped | F9: FY25: PSU CASA edges past private for the first time.
A11: 5 Key Findings
A12: #1 | B12: ROA gap held at ~1 percentage point. | C12: Private ROA doubled (0.97% → 1.98%). PSU ROA grew 7× from a tiny base (0.16% → 1.12%). The gap is structural.
A13: #2 | B13: The PSU NPA clean-up is real — and almost over. | C13: PSU gross NPA fell from 9.92% → 2.68%. Excess vs private fell from 6.04pp to 1.23pp. The easy gains are done.
A14: #3 | B14: PSUs aren't growth-laggards, they're just smaller. | C14: PNB loan-book CAGR 18.8%, SBI 12.7% — same range as ICICI/Axis. The 'PSUs are dying' narrative is wrong.
A15: #4 | B15: The CASA advantage just evaporated. | C15: Private CASA peaked at 47.4% (FY22) → 38.1% (FY25). In FY25 PSUs (39.6%) actually beat private.
A16: #5 | B16: NIM: the persistent ~90bps spread. | C16: Private banks earn ~90bps more on every rupee they lend — pricing power & retail mix, not luck.
A18: 3 Strategic Recommendations for the PSU CEO
A19: 1 | B19: Stop chasing CASA. Chase NIM. | C19: The CASA war is over and the rate cycle decided it. Shift 5pp of the loan book from corporate to high-yield retail by FY27; stand up a digital-lending JV.
A20: 2 | B20: Defend NPA gains by re-engineering underwriting, not lending less. | C20: IBC won the first NPA war. Win the second with data: bureau scores, GST flows, real-time monitoring. Mandate model-driven decisions for loans under ₹5cr.
A21: 3 | B21: Become the bank for Bharat's middle 60%. | C21: 600M middle-income, semi-urban, GST-registered SMBs are under-served. PSUs have the trust and branches — close the digital UX gap. Target ₹5 lakh crore new SMB advances by FY28.

Sheet Raw Data
A1: Bank-year master dataset (FY20–FY25)
A2: Absolute values in ₹ crore. Ratios in percent. Source: each bank's annual report + investor presentations + Equitymaster + verified via May 2026 web search.
A4: bank_name | B4: bank_type | C4: financial_year | D4: total_assets_cr | E4: deposits_cr | F4: advances_cr | G4: net_profit_cr | H4: gross_npa_pct | I4: roa_pct | J4: nim_pct | K4: casa_pct
A5: HDFC Bank | B5: Private | C5: FY20 | D5: 1530511 | E5: 1147502 | F5: 993703 | G5: 26257 | H5: 1.26 | I5: 1.89 | J5: 4.2 | K5: 42.2
A6: HDFC Bank | B6: Private | C6: FY21 | D6: 1746870 | E6: 1335060 | F6: 1132837 | G6: 31116 | H6: 1.32 | I6: 1.97 | J6: 4.1 | K6: 46.1
A7: HDFC Bank | B7: Private | C7: FY22 | D7: 2068535 | E7: 1559217 | F7: 1368821 | G7: 36961 | H7: 1.17 | I7: 2.03 | J7: 4 | K7: 48.2
A8: HDFC Bank | B8: Private | C8: FY23 | D8: 2466081 | E8: 1883394 | F8: 1600586 | G8: 44109 | H8: 1.12 | I8: 2.07 | J8: 4.1 | K8: 44.4
A9: HDFC Bank | B9: Private | C9: FY24 | D9: 4030190 | E9: 2376888 | F9: 2571920 | G9: 64062 | H9: 1.24 | I9: 1.59 | J9: 3.6 | K9: 38.2
A10: HDFC Bank | B10: Private | C10: FY25 | D10: 4392420 | E10: 2710900 | F10: 2724940 | G10: 70792 | H10: 1.33 | I10: 1.61 | J10: 3.9 | K10: 34.9
A11: ICICI Bank | B11: Private | C11: FY20 | D11: 1098365 | E11: 770968 | F11: 645289 | G11: 7931 | H11: 5.53 | I11: 0.81 | J11: 3.73 | K11: 45.1
A12: ICICI Bank | B12: Private | C12: FY21 | D12: 1230433 | E12: 932522 | F12: 733729 | G12: 16193 | H12: 4.96 | I12: 1.42 | J12: 3.69 | K12: 46.3
A13: ICICI Bank | B13: Private | C13: FY22 | D13: 1411297 | E13: 1064571 | F13: 859020 | G13: 23339 | H13: 3.6 | I13: 1.84 | J13: 3.96 | K13: 48.9
A14: ICICI Bank | B14: Private | C14: FY23 | D14: 1584207 | E14: 1180840 | F14: 1019638 | G14: 31896 | H14: 2.81 | I14: 2.13 | J14: 4.48 | K14: 45.8
A15: ICICI Bank | B15: Private | C15: FY24 | D15: 1729021 | E15: 1412825 | F15: 1184406 | G15: 40888 | H15: 2.3 | I15: 2.37 | J15: 4.1 | K15: 42
A16: ICICI Bank | B16: Private | C16: FY25 | D16: 1918233 | E16: 1610348 | F16: 1341766 | G16: 47227 | H16: 1.7 | I16: 2.46 | J16: 4.4 | K16: 38.4
... A40: Bank of Baroda | B40: PSU | C40: FY25 | D40: 1710000 | E40: 1472000 | F40: 1230000 | G40: 20716 | H40: 2.26 | I40: 1.26 | J40: 3.02 | K40: 39.95

Sheet Group Averages
A1: Year-by-year averages — Private vs PSU
A3: ROA (%)
A4: Year | B4: Private | C4: PSU | D4: Gap (pp)
A5: FY20 | B5: =AVERAGEIFS('Raw Data'!I:I,'Raw Data'!B:B,"Private",'Raw Data'!C:C,"FY20") -> 0.96666667 | C5: =AVERAGEIFS('Raw Data'!I:I,'Raw Data'!B:B,"PSU",'Raw Data'!C:C,"FY20") -> 0.16 | D5: =B5-C5 -> 0.80666667
A6: FY21 | B6: =AVERAGEIFS('Raw Data'!I:I,'Raw Data'!B:B,"Private",'Raw Data'!C:C,"FY21") -> 1.3633333 | C6: =AVERAGEIFS('Raw Data'!I:I,'Raw Data'!B:B,"PSU",'Raw Data'!C:C,"FY21") -> 0.23333333 | D6: =B6-C6 -> 1.13
A7: FY22 | B7: =AVERAGEIFS('Raw Data'!I:I,'Raw Data'!B:B,"Private",'Raw Data'!C:C,"FY22") -> 1.6933333 | C7: =AVERAGEIFS('Raw Data'!I:I,'Raw Data'!B:B,"PSU",'Raw Data'!C:C,"FY22") -> 0.51 | D7: =B7-C7 -> 1.1833333
A8: FY23 | B8: =AVERAGEIFS('Raw Data'!I:I,'Raw Data'!B:B,"Private",'Raw Data'!C:C,"FY23") -> 1.67 | C8: =AVERAGEIFS('Raw Data'!I:I,'Raw Data'!B:B,"PSU",'Raw Data'!C:C,"FY23") -> 0.72333333 | D8: =B8-C8 -> 0.94666667
A9: FY24 | B9: =AVERAGEIFS('Raw Data'!I:I,'Raw Data'!B:B,"Private",'Raw Data'!C:C,"FY24") -> 1.93 | C9: =AVERAGEIFS('Raw Data'!I:I,'Raw Data'!B:B,"PSU",'Raw Data'!C:C,"FY24") -> 0.92 | D9: =B9-C9 -> 1.01
A10: FY25 | B10: =AVERAGEIFS('Raw Data'!I:I,'Raw Data'!B:B,"Private",'Raw Data'!C:C,"FY25") -> 1.9833333 | C10: =AVERAGEIFS('Raw Data'!I:I,'Raw Data'!B:B,"PSU",'Raw Data'!C:C,"FY25") -> 1.12 | D10: =B10-C10 -> 0.86333333
A13: Gross NPA (%)
A14: Year | B14: Private | C14: PSU | D14: Gap (pp)
A15: FY20 | B15: =AVERAGEIFS('Raw Data'!H:H,'Raw Data'!B:B,"Private",'Raw Data'!C:C,"FY20") -> 3.8833333 | C15: =AVERAGEIFS('Raw Data'!H:H,'Raw Data'!B:B,"PSU",'Raw Data'!C:C,"FY20") -> 9.92 | D15: =B15-C15 -> -6.0366667
A16: FY21 | B16: =AVERAGEIFS('Raw Data'!H:H,'Raw Data'!B:B,"Private",'Raw Data'!C:C,"FY21") -> 3.3266667 | C16: =AVERAGEIFS('Raw Data'!H:H,'Raw Data'!B:B,"PSU",'Raw Data'!C:C,"FY21") -> 9.3233333 | D16: =B16-C16 -> -5.9966667
A17: FY22 | B17: =AVERAGEIFS('Raw Data'!H:H,'Raw Data'!B:B,"Private",'Raw Data'!C:C,"FY22") -> 2.53 | C17: =AVERAGEIFS('Raw Data'!H:H,'Raw Data'!B:B,"PSU",'Raw Data'!C:C,"FY22") -> 7.4533333 | D17: =B17-C17 -> -4.9233333
A18: FY23 | B18: =AVERAGEIFS('Raw Data'!H:H,'Raw Data'!B:B,"Private",'Raw Data'!C:C,"FY23") -> 1.9833333 | C18: =AVERAGEIFS('Raw Data'!H:H,'Raw Data'!B:B,"PSU",'Raw Data'!C:C,"FY23") -> 5.1033333 | D18: =B18-C18 -> -3.12
A19: FY24 | B19: =AVERAGEIFS('Raw Data'!H:H,'Raw Data'!B:B,"Private",'Raw Data'!C:C,"FY24") -> 1.68 | C19: =AVERAGEIFS('Raw Data'!H:H,'Raw Data'!B:B,"PSU",'Raw Data'!C:C,"FY24") -> 3.63 | D19: =B19-C19 -> -1.95
A20: FY25 | B20: =AVERAGEIFS('Raw Data'!H:H,'Raw Data'!B:B,"Private",'Raw Data'!C:C,"FY25") -> 1.4433333 | C20: =AVERAGEIFS('Raw Data'!H:H,'Raw Data'!B:B,"PSU",'Raw Data'!C:C,"FY25") -> 2.6766667 | D20: =B20-C20 -> -1.2333333
A23: NIM (%)
A24: Year | B24: Private | C24: PSU | D24: Gap (pp)
A25: FY20 | B25: =AVERAGEIFS('Raw Data'!J:J,'Raw Data'!B:B,"Private",'Raw Data'!C:C,"FY20") -> 3.8133333 | C25: =AVERAGEIFS('Raw Data'!J:J,'Raw Data'!B:B,"PSU",'Raw Data'!C:C,"FY20") -> 2.7966667 | D25: =B25-C25 -> 1.0166667
A26: FY21 | B26: =AVERAGEIFS('Raw Data'!J:J,'Raw Data'!B:B,"Private",'Raw Data'!C:C,"FY21") -> 3.7733333 | C26: =AVERAGEIFS('Raw Data'!J:J,'Raw Data'!B:B,"PSU",'Raw Data'!C:C,"FY21") -> 2.9966667 | D26: =B26-C26 -> 0.77666667
A27: FY22 | B27: =AVERAGEIFS('Raw Data'!J:J,'Raw Data'!B:B,"Private",'Raw Data'!C:C,"FY22") -> 3.81 | C27: =AVERAGEIFS('Raw Data'!J:J,'Raw Data'!B:B,"PSU",'Raw Data'!C:C,"FY22") -> 2.9533333 | D27: =B27-C27 -> 0.85666667
A28: FY23 | B28: =AVERAGEIFS('Raw Data'!J:J,'Raw Data'!B:B,"Private",'Raw Data'!C:C,"FY23") -> 4.2 | C28: =AVERAGEIFS('Raw Data'!J:J,'Raw Data'!B:B,"PSU",'Raw Data'!C:C,"FY23") -> 3.2466667 | D28: =B28-C28 -> 0.95333333
A29: FY24 | B29: =AVERAGEIFS('Raw Data'!J:J,'Raw Data'!B:B,"Private",'Raw Data'!C:C,"FY24") -> 3.8666667 | C29: =AVERAGEIFS('Raw Data'!J:J,'Raw Data'!B:B,"PSU",'Raw Data'!C:C,"FY24") -> 3.2133333 | D29: =B29-C29 -> 0.65333333
A30: FY25 | B30: =AVERAGEIFS('Raw Data'!J:J,'Raw Data'!B:B,"Private",'Raw Data'!C:C,"FY25") -> 4.0933333 | C30: =AVERAGEIFS('Raw Data'!J:J,'Raw Data'!B:B,"PSU",'Raw Data'!C:C,"FY25") -> 3.0133333 | D30: =B30-C30 -> 1.08
A33: CASA (%)
A34: Year | B34: Private | C34: PSU | D34: Gap (pp)
A35: FY20 | B35: =AVERAGEIFS('Raw Data'!K:K,'Raw Data'!B:B,"Private",'Raw Data'!C:C,"FY20") -> 42.833333 | C35: =AVERAGEIFS('Raw Data'!K:K,'Raw Data'!B:B,"PSU",'Raw Data'!C:C,"FY20") -> 42.333333 | D35: =B35-C35 -> 0.5
A36: FY21 | B36: =AVERAGEIFS('Raw Data'!K:K,'Raw Data'!B:B,"Private",'Raw Data'!C:C,"FY21") -> 45.8 | C36: =AVERAGEIFS('Raw Data'!K:K,'Raw Data'!B:B,"PSU",'Raw Data'!C:C,"FY21") -> 44.5 | D36: =B36-C36 -> 1.3
A37: FY22 | B37: =AVERAGEIFS('Raw Data'!K:K,'Raw Data'!B:B,"Private",'Raw Data'!C:C,"FY22") -> 47.366667 | C37: =AVERAGEIFS('Raw Data'!K:K,'Raw Data'!B:B,"PSU",'Raw Data'!C:C,"FY22") -> 44.933333 | D37: =B37-C37 -> 2.4333333
A38: FY23 | B38: =AVERAGEIFS('Raw Data'!K:K,'Raw Data'!B:B,"Private",'Raw Data'!C:C,"FY23") -> 45.733333 | C38: =AVERAGEIFS('Raw Data'!K:K,'Raw Data'!B:B,"PSU",'Raw Data'!C:C,"FY23") -> 42.366667 | D38: =B38-C38 -> 3.3666667
A39: FY24 | B39: =AVERAGEIFS('Raw Data'!K:K,'Raw Data'!B:B,"Private",'Raw Data'!C:C,"FY24") -> 40.733333 | C39: =AVERAGEIFS('Raw Data'!K:K,'Raw Data'!B:B,"PSU",'Raw Data'!C:C,"FY24") -> 40.666667 | D39: =B39-C39 -> 0.066666667
A40: FY25 | B40: =AVERAGEIFS('Raw Data'!K:K,'Raw Data'!B:B,"Private",'Raw Data'!C:C,"FY25") -> 38.1 | C40: =AVERAGEIFS('Raw Data'!K:K,'Raw Data'!B:B,"PSU",'Raw Data'!C:C,"FY25") -> 39.573333 | D40: =B40-C40 -> -1.4733333

Sheet FY25 League Table
A1: FY25 — All 6 banks ranked best-to-worst
A3: Rank | B3: Bank | C3: Type | D3: Total assets (₹cr) | E3: Net profit (₹cr) | F3: ROA (%) | G3: Gross NPA (%) | H3: NIM (%) | I3: CASA (%)
A4: 1 | B4: Axis Bank | C4: Private | D4: 1610327 | E4: 28055 | F4: 1.88 | G4: 1.3 | H4: 3.98 | I4: 41
A5: 2 | B5: ICICI Bank | C5: Private | D5: 1918233 | E5: 47227 | F5: 2.46 | G5: 1.7 | H5: 4.4 | I5: 38.4
A6: 3 | B6: HDFC Bank | C6: Private | D6: 4392420 | E6: 70792 | F6: 1.61 | G6: 1.33 | H6: 3.9 | I6: 34.9
A7: 3 | B7: SBI | C7: PSU | D7: 6606290 | E7: 70901 | F7: 1.1 | G7: 1.82 | H7: 3.09 | I7: 39.97
A8: 5 | B8: Bank of Baroda | C8: PSU | D8: 1710000 | E8: 20716 | F8: 1.26 | G8: 2.26 | H8: 3.02 | I8: 39.95
A9: 6 | B9: PNB | C9: PSU | D9: 1650000 | E9: 16630 | F9: 1 | G9: 3.95 | H9: 2.93 | I9: 38.8
A11: Note: SBI ties HDFC on ranks — only PSU competitive across every dimension. PNB still last.
